samsung_mdc_ctl/__init__.py
samsung_mdc_ctl/__main__.py
samsung_mdc_ctl/example.py
samsung_mdc_ctl/helpers/aspect.py
samsung_mdc_ctl/helpers/connection.py
samsung_mdc_ctl/helpers/display_status.py
samsung_mdc_ctl/helpers/exceptions.py
samsung_mdc_ctl/helpers/model.py
samsung_mdc_ctl/helpers/panel_type.py
samsung_mdc_ctl/helpers/status.py
samsung_mdc_ctl/mdc_display.py
samsung_mdc_ctl/protocol/commands.py
samsung_mdc_ctl/protocol/power.py
samsung_mdc_ctl/protocol/response.py
samsung_mdc_ctl/protocol/sources.py
samsung_mdc_ctl/protocol/virtual_remote_keys.py
samsung_mdc_ctl/py.typed
samsung_mdc_ctl/utils.py
samsung_mdc_ctl-0.2.3.dist-info/entry_points.txt
samsung_mdc_ctl-0.2.3.dist-info/LICENSE
samsung_mdc_ctl-0.2.3.dist-info/WHEEL
samsung_mdc_ctl-0.2.3.dist-info/METADATA
samsung_mdc_ctl-0.2.3.dist-info/RECORD
