Metadata-Version: 2.1
Name: samsung-mdc-ctl
Version: 0.2.3
Summary: Awesome `samsung-mdc-ctl` is a Python cli/package created with https://github.com/TezRomacH/python-package-template
Home-page: https://github.com/matthijs2704/samsung-mdc-ctl
License: MIT
Author: matthijs2704
Author-email: matthijs@logemann.dev
Requires-Python: >=3.7,<4.0
Classifier: Development Status :: 3 - Alpha
Classifier: Intended Audience :: Developers
Classifier: License :: OSI Approved :: MIT License
Classifier: Operating System :: OS Independent
Classifier: Programming Language :: Python :: 3
Classifier: Programming Language :: Python :: 3.7
Classifier: Programming Language :: Python :: 3.8
Classifier: Programming Language :: Python :: 3.9
Classifier: Topic :: Software Development :: Libraries :: Python Modules
Requires-Dist: importlib_metadata (>=3.7.3,<4.0.0); python_version < "3.8"
Requires-Dist: rich (>=9.8.2,<10.0.0)
Requires-Dist: typer[all] (>=0.3.2,<0.4.0)
Project-URL: Repository, https://github.com/matthijs2704/samsung-mdc-ctl
